plunkylib/__init__.py
plunkylib/__main__.py
plunkylib/aiwrapper.py
plunkylib/plunkycli.py
plunkylib/plunkycore.py
plunkylib-0.1.5.dist-info/entry_points.txt
plunkylib-0.1.5.dist-info/LICENSE
plunkylib-0.1.5.dist-info/METADATA
plunkylib-0.1.5.dist-info/WHEEL
plunkylib-0.1.5.dist-info/RECORD
