Metadata-Version: 2.1
Name: plunkylib
Version: 0.1.5
Summary: plunkylib - Python LLM User Navigation Kit via YAML
License: MIT
Author: Mattie Casper
Requires-Python: >=3.10,<4.0
Classifier: License :: OSI Approved :: MIT License
Classifier: Programming Language :: Python :: 3
Classifier: Programming Language :: Python :: 3.10
Classifier: Programming Language :: Python :: 3.11
Requires-Dist: datafiles (>=2.0,<3.0)
Requires-Dist: loguru (>=0.6.0,<0.7.0)
Requires-Dist: nest-asyncio (>=1.5.6,<2.0.0)
Requires-Dist: openai (>=0.27.2,<0.28.0)
Requires-Dist: python-dotenv (>=1.0.0,<2.0.0)
Requires-Dist: typer (>=0.7.0,<0.8.0)
